{
  "flows": [
    {
      "path": "ns3::RdmaFlowUnicast",
      "enable": false,
      "start_time": 0.0,
      "in_background": false,
      "attributes": {
        "SourceNode": 100,
        "DestinationNode": 101,
        "IsReliable": false,
        "PfcPriority": 3,
        "WriteByteAmount": 1e6
      }
    },
    {
      "path": "ns3::AgFlowMcastPhase",
      "enable": true,
      "start_time": 0.0,
      "in_background": false,
      "attributes": {
        "BitmapsAvroOut": "out_recv_chunks.avro",
        "MulticastRootCount": 2,
        "PerNodeChunkCount": 3,
        "PerChunkPacketCount": 2
      }
    }
  ]
}